throughput/image.py
throughput-0.0.2.dist-info/licenses/LICENSE
throughput-0.0.2.dist-info/METADATA
throughput-0.0.2.dist-info/WHEEL
throughput-0.0.2.dist-info/top_level.txt
throughput-0.0.2.dist-info/RECORD
